{
  "contacts": [
    {
      "id": "TvobxeKbI",
      "name": "Glenda ",
      "lastname": "Kim",
      "fieldofemployment": "JAVA Developer",
      "about": "",
      "groupId": "2"
    },
    {
      "id": "kLt-bJF",
      "name": "Rajan ",
      "lastname": "Das",
      "fieldofemployment": "Software Engineer",
      "about": "",
      "groupId": "1"
    },
    {
      "name": "abhishek",
      "lastname": "Malgi",
      "titfieldofemploymentle": "Full Stack Web Developer",
      "about": "",
      "groupId": "1",
      "id": "JgqsD5s",
      "fieldofemployment": "Front end Developer"
    },
    {
      "name": "Sagar ",
      "groupId": "3",
      "lastname": "metri",
      "fieldofemployment": "full stack developer",
      "about": "abhhdbcsdnehiubhiuh",
      "id": "D8yXn8n"
    },
    {
      "name": "shreenidhi ",
      "lastname": "k",
      "fieldofemployment": "ansys designer",
      "about": "dajdjadoiajdaoij",
      "groupId": "2",
      "id": "Omx6bzQ"
    }
  ],
  "groups": [
    {
      "id": "1",
      "name": "CSS"
    },
    {
      "id": "2",
      "name": "HTML"
    },
    {
      "id": "3",
      "name": "JavaScript"
    },
    {
      "id": "4",
      "name": "JAVA"
    },
    {
      "id": "5",
      "name": "React.JS"
    },
    {
      "id": "6",
      "name": "Python"
    }
  ]
}